Metadata-Version: 2.1
Name: contributions-django
Version: 0.0.0
Summary: A GitHub style contributions graph for Django
Home-page: https://github.com/vsoch/contributions_django
Author: Vanessa Sochat
Author-email: vsochat@stanford.edu
License: Apache Software License 2.0
Keywords: contributions_django
Platform: UNKNOWN
Classifier: Development Status :: 3 - Alpha
Classifier: Framework :: Django :: 2.1
Classifier: Intended Audience :: Developers
Classifier: License :: OSI Approved :: Apache Software License
Classifier: Natural Language :: English
Classifier: Programming Language :: Python :: 3
Classifier: Programming Language :: Python :: 3.5
Classifier: Programming Language :: Python :: 3.6
